rosmontis/__init__.py
rosmontis/rosmontis.py
rosmontis-1.0.0.dist-info/METADATA
rosmontis-1.0.0.dist-info/WHEEL
rosmontis-1.0.0.dist-info/top_level.txt
rosmontis-1.0.0.dist-info/RECORD
